{
	"format_version": "1.20.80",
	"minecraft:block": {
		"description": {
			"identifier": "utilitycraft:crusher",
			"menu_category": {
				"category": "construction"
			},
			"states": {
				"utilitycraft:refreshSpeed": [
					1,
					5,
					10,
					20,
					40
				],
				"utilitycraft:on": [
					false,
					true
				]
			},
			"traits": {
				"minecraft:placement_direction": {
					"enabled_states": [
						"minecraft:facing_direction"
					]
				}
			}
		},
		"components": {
			"utilitycraft:crusher": {
				"entity": "utilitycraft:machine_general",
				"name_tag": "entity.utilitycraft:crusher.name",
				"energy_cost": 800,
				"rate_speed_base": 20,
				"energy_cap": 64000,
				"upgrades": [
					4,
					5
				],
				"recipes": "crushing"
			},
			"minecraft:geometry": "geometry.utilitycraft_block_2",
			"minecraft:material_instances": {
				"*": {
					"texture": "utilitycraft_crusher_off",
					"render_method": "alpha_test"
				}
			},
			"minecraft:tick": {
				"interval_range": [
					5,
					5
				]
			},
			"minecraft:destructible_by_mining": {
				"seconds_to_destroy": 1
			},
			"minecraft:destructible_by_explosion": false,
			"tag:dorios:energy": {},
			"tag:dorios:item": {},
			"tag:minecraft_is_pickaxe_item_destructible": {}
		},
		"permutations": [
			{
				"condition": "q.block_state('utilitycraft:refreshSpeed') == 1 ",
				"components": {
					"minecraft:tick": {
						"interval_range": [
							5,
							5
						]
					}
				}
			},
			{
				"condition": "q.block_state('utilitycraft:refreshSpeed') == 5 ",
				"components": {
					"minecraft:tick": {
						"interval_range": [
							25,
							25
						]
					}
				}
			},
			{
				"condition": "q.block_state('utilitycraft:refreshSpeed') == 10 ",
				"components": {
					"minecraft:tick": {
						"interval_range": [
							50,
							50
						]
					}
				}
			},
			{
				"condition": "q.block_state('utilitycraft:refreshSpeed') == 20 ",
				"components": {
					"minecraft:tick": {
						"interval_range": [
							100,
							100
						]
					}
				}
			},
			{
				"condition": "q.block_state('utilitycraft:refreshSpeed') == 40 ",
				"components": {
					"minecraft:tick": {
						"interval_range": [
							200,
							200
						]
					}
				}
			},
			{
				"condition": "q.block_state('minecraft:facing_direction') == 'up'",
				"components": {
					"minecraft:transformation": {
						"rotation": [
							-90,
							0,
							0
						]
					}
				}
			},
			{
				"condition": "q.block_state('minecraft:facing_direction') == 'down' ",
				"components": {
					"minecraft:transformation": {
						"rotation": [
							90,
							0,
							0
						]
					}
				}
			},
			{
				"condition": "q.block_state('minecraft:facing_direction') == 'north' ",
				"components": {
					"minecraft:transformation": {
						"rotation": [
							0,
							180,
							0
						]
					}
				}
			},
			{
				"condition": "q.block_state('minecraft:facing_direction') == 'south' ",
				"components": {
					"minecraft:transformation": {
						"rotation": [
							0,
							0,
							0
						]
					}
				}
			},
			{
				"condition": "q.block_state('minecraft:facing_direction') == 'east' ",
				"components": {
					"minecraft:transformation": {
						"rotation": [
							0,
							90,
							0
						]
					}
				}
			},
			{
				"condition": "q.block_state('minecraft:facing_direction') == 'west' ",
				"components": {
					"minecraft:transformation": {
						"rotation": [
							0,
							-90,
							0
						]
					}
				}
			},
			{
				"condition": "q.block_state('utilitycraft:on') == true ",
				"components": {
					"minecraft:material_instances": {
						"*": {
							"texture": "utilitycraft_crusher_on",
							"render_method": "alpha_test"
						}
					}
				}
			}
		]
	}
}